crawl4ai_mcp/__init__.py
crawl4ai_mcp/server.py
crawl4ai_mcp/utils.py
crawl4ai_mcp_server-0.1.5.dist-info/licenses/LICENSE
crawl4ai_mcp_server-0.1.5.dist-info/METADATA
crawl4ai_mcp_server-0.1.5.dist-info/WHEEL
crawl4ai_mcp_server-0.1.5.dist-info/entry_points.txt
crawl4ai_mcp_server-0.1.5.dist-info/top_level.txt
crawl4ai_mcp_server-0.1.5.dist-info/RECORD
