Metadata-Version: 2.4
Name: crawl4ai-mcp-server
Version: 0.1.5
Summary: A Model Context Protocol server for web crawling using Crawl4ai
Author-email: Your Name <your.email@example.com>
License: MIT
Project-URL: Homepage, https://github.com/yourusername/crawl4ai-mcp-server
Project-URL: Bug Tracker, https://github.com/yourusername/crawl4ai-mcp-server/issues
Classifier: Programming Language :: Python :: 3
Classifier: License :: OSI Approved :: MIT License
Classifier: Operating System :: OS Independent
Requires-Python: >=3.8
License-File: LICENSE
Requires-Dist: mcp>=1.0.0
Requires-Dist: crawl4ai
Requires-Dist: pydantic
Requires-Dist: playwright
Requires-Dist: pydantic
Requires-Dist: asyncio
Dynamic: license-file
